esmvalcore/__init__.py
esmvalcore/_citation.py
esmvalcore/_main.py
esmvalcore/_provenance.py
esmvalcore/_task.py
esmvalcore/_version.py
esmvalcore/config-developer.yml
esmvalcore/dataset.py
esmvalcore/exceptions.py
esmvalcore/iris_helpers.py
esmvalcore/local.py
esmvalcore/typing.py
esmvalcore/_recipe/__init__.py
esmvalcore/_recipe/_io.py
esmvalcore/_recipe/check.py
esmvalcore/_recipe/from_datasets.py
esmvalcore/_recipe/recipe.py
esmvalcore/_recipe/recipe_schema.yml
esmvalcore/_recipe/to_datasets.py
esmvalcore/cmor/__init__.py
esmvalcore/cmor/_utils.py
esmvalcore/cmor/check.py
esmvalcore/cmor/fix.py
esmvalcore/cmor/fixes.py
esmvalcore/cmor/table.py
esmvalcore/cmor/variable_alt_names.yml
esmvalcore/cmor/_fixes/__init__.py
esmvalcore/cmor/_fixes/common.py
esmvalcore/cmor/_fixes/fix.py
esmvalcore/cmor/_fixes/native_datasets.py
esmvalcore/cmor/_fixes/shared.py
esmvalcore/cmor/_fixes/us_standard_atmosphere.csv
esmvalcore/cmor/_fixes/access/__init__.py
esmvalcore/cmor/_fixes/access/_base_fix.py
esmvalcore/cmor/_fixes/access/access_esm1_5.py
esmvalcore/cmor/_fixes/cesm/__init__.py
esmvalcore/cmor/_fixes/cesm/cesm2.py
esmvalcore/cmor/_fixes/cmip5/__init__.py
esmvalcore/cmor/_fixes/cmip5/access1_0.py
esmvalcore/cmor/_fixes/cmip5/access1_3.py
esmvalcore/cmor/_fixes/cmip5/bcc_csm1_1.py
esmvalcore/cmor/_fixes/cmip5/bcc_csm1_1_m.py
esmvalcore/cmor/_fixes/cmip5/bnu_esm.py
esmvalcore/cmor/_fixes/cmip5/canesm2.py
esmvalcore/cmor/_fixes/cmip5/ccsm4.py
esmvalcore/cmor/_fixes/cmip5/cesm1_bgc.py
esmvalcore/cmor/_fixes/cmip5/cesm1_cam5.py
esmvalcore/cmor/_fixes/cmip5/cesm1_fastchem.py
esmvalcore/cmor/_fixes/cmip5/cesm1_waccm.py
esmvalcore/cmor/_fixes/cmip5/cnrm_cm5.py
esmvalcore/cmor/_fixes/cmip5/csiro_mk3_6_0.py
esmvalcore/cmor/_fixes/cmip5/ec_earth.py
esmvalcore/cmor/_fixes/cmip5/fgoals_g2.py
esmvalcore/cmor/_fixes/cmip5/fgoals_s2.py
esmvalcore/cmor/_fixes/cmip5/fio_esm.py
esmvalcore/cmor/_fixes/cmip5/gfdl_cm2p1.py
esmvalcore/cmor/_fixes/cmip5/gfdl_cm3.py
esmvalcore-2.13.0.dist-info/licenses/LICENSE
esmvalcore-2.13.0.dist-info/METADATA
esmvalcore-2.13.0.dist-info/WHEEL
esmvalcore-2.13.0.dist-info/entry_points.txt
esmvalcore-2.13.0.dist-info/top_level.txt
esmvalcore-2.13.0.dist-info/RECORD
